LICENSE
MANIFEST.in
README.md
setup.py
testflows.database.egg-info/PKG-INFO
testflows.database.egg-info/SOURCES.txt
testflows.database.egg-info/dependency_links.txt
testflows.database.egg-info/not-zip-safe
testflows.database.egg-info/requires.txt
testflows.database.egg-info/top_level.txt
testflows/database/__init__.py
testflows/database/argparser.py
testflows/database/base.py
testflows/database/clickhouse.py
testflows/database/handler.py
testflows/database/pipeline.py
testflows/database/_clickhouse/__init__.py
testflows/database/_clickhouse/database.py
testflows/database/_clickhouse/schema.py
testflows/database/_clickhouse/transform.py
testflows/database/cli/__init__.py
testflows/database/cli/create.py
testflows/database/cli/handler.py